pigeonXT/__init__.py
pigeonXT/__version__.py
pigeonXT/analyse.py
pigeonXT/annotate.py
pigeonxt_jupyter-0.7.3.dist-info/LICENSE
pigeonxt_jupyter-0.7.3.dist-info/WHEEL
pigeonxt_jupyter-0.7.3.dist-info/METADATA
pigeonxt_jupyter-0.7.3.dist-info/RECORD
