Metadata-Version: 2.1
Name: pigeonxt-jupyter
Version: 0.7.3
Summary: Quickly annotate data in Jupyter notebooks.
Home-page: https://github.com/dennisbakhuis/pigeonXT
License: Apache 2.0
Keywords: artificial inteligence,labeling,jupyter,machine learning,data science,data,science
Author: Dennis Bakhuis
Author-email: pypi@bakhuis.nu
Requires-Python: >=3.9,<4.0
Classifier: License :: Other/Proprietary License
Classifier: Programming Language :: Python :: 3
Classifier: Programming Language :: Python :: 3.9
Classifier: Programming Language :: Python :: 3.10
Classifier: Programming Language :: Python :: 3.11
Requires-Dist: ipywidgets (>=8.0,<9.0)
Requires-Dist: jupyterlab (>=3.3,<4.0)
Requires-Dist: numpy (>=1.23,<2.0)
Requires-Dist: pandas (>=1.3,<2.0)
Project-URL: Repository, https://github.com/dennisbakhuis/pigeonXT
